Metadata-Version: 1.1
Name: azure-storage-logging
Version: 0.3.0
Summary: Logging handlers to send logging output to Microsoft Azure Storage
Home-page: https://github.com/michiya/azure-storage-logging
Author: Michiya Takahashi
Author-email: michiya.takahashi@gmail.com
License: Apache License 2.0
Keywords: azure logging
Platform: UNKNOWN
Classifier: Development Status :: 4 - Beta
Classifier: License :: OSI Approved :: Apache Software License
Classifier: Programming Language :: Python
Classifier: Programming Language :: Python :: 2
Classifier: Programming Language :: Python :: 2.7
Classifier: Programming Language :: Python :: 3
Classifier: Programming Language :: Python :: 3.3
Classifier: Programming Language :: Python :: 3.4
Classifier: Topic :: System :: Logging
